sympkf/__init__.py
sympkf/dynamics/__init__.py
sympkf/dynamics/burgers.py
sympkf/model/__init__.py
sympkf/model/model.py
sympkf/symbolic/__init__.py
sympkf/symbolic/constants.py
sympkf/symbolic/dynamics.py
sympkf/symbolic/finite_difference.py
sympkf/symbolic/model_builder.py
sympkf/symbolic/model_builder_FD.py
sympkf/symbolic/model_builder_manifold.py
sympkf/symbolic/pkfcas.py
sympkf/symbolic/random.py
sympkf/symbolic/tool.py
sympkf/symbolic/util.py
sympkf/symbolic/templates/__init__.py
sympkf/symbolic/templates/body_FDModelBuilder.py
sympkf/symbolic/templates/body_ManifoldModelBuilder.py
sympkf/symbolic/templates/footer.py
sympkf/symbolic/templates/header.py
sympkf/symbolic/templates/licence.py
sympkf/symbolic/test/__init__.py
sympkf/symbolic/test/test_PKFSystem.py
sympkf/symbolic/test/test_PartialOrderDerivative.py
sympkf/symbolic/test/test_code.py
sympkf/symbolic/test/test_consistancy.py
sympkf/symbolic/test/test_coordinate.py
sympkf/symbolic/test/test_random_Expectation.py
sympkf/symbolic/test/test_random_israndom.py
sympkf/symbolic/test/test_util_Eq.py
sympkf-1.0.6.dist-info/LICENCE.txt
sympkf-1.0.6.dist-info/METADATA
sympkf-1.0.6.dist-info/WHEEL
sympkf-1.0.6.dist-info/top_level.txt
sympkf-1.0.6.dist-info/RECORD
