Metadata-Version: 2.1
Name: sympkf
Version: 1.0.6
Summary: Symbolic Calculation for the Parametric Dynamics
Home-page: https://github.com/opannekoucke/sympkf
Author: Olivier Pannekoucke 
Author-email: olivier.pannekoucke@meteo.fr
Project-URL: Bug Tracker, https://github.com/opannekoucke/sympkf/issues
Classifier: Programming Language :: Python :: 3
Classifier: License :: CeCILL-B Free Software License Agreement (CECILL-B) 
Classifier: Operating System :: OS Independent
Requires-Python: >=3.6
License-File: LICENCE.txt
